{
  "id": "album_the-prodigal-son",
  "type": "album",
  "title": "The Prodigal Son",
  "description": "Bobby Blaze v roce 2021 vydal své třetí album. Obsahuje celkem 14 skladeb, což je o 3 skladby více, než je u Bobby Blaze zvykem. Deska vyšla pod labelem 1204588 Records DK.",
  "slug": "the-prodigal-son",
  "image": "https://cdn-images.dzcdn.net/images/cover/2e73613acd7fdbebd5e6e00c1062eba4/1000x1000-000000-80-0-0.jpg",
  "publishedAt": "2021-01-01",
  "year": 2021,
  "trackCount": 11,
  "durationSec": 2992,
  "deezerId": 62938892,
  "label": "Fantasy Records",
  "upc": "888072049130",
  "genres": [
    "rock"
  ],
  "sourceUrls": {
    "deezer": "https://www.deezer.com/album/62938892"
  }
}