{
  "id": "track_aezakmi-vercetti-cg",
  "kind": "track",
  "slug": "aezakmi-vercetti-cg",
  "title": "AEZAKMI",
  "aliases": [],
  "summary": "",
  "status": "stub",
  "createdAt": "2026-05-31",
  "updatedAt": "2026-05-31",
  "meta": {
    "primaryArtist": {
      "kind": "rapper",
      "slug": "sakito"
    },
    "features": [
      {
        "kind": "rapper",
        "slug": "vercetti-cg"
      }
    ],
    "album": {
      "kind": "album",
      "slug": "splitscreen"
    },
    "producers": [],
    "year": 2025,
    "duration": "2:26",
    "trackNumber": 5,
    "genres": []
  },
  "significance": {
    "why": "",
    "whatChanged": "",
    "context": "",
    "distinguishing": "",
    "oneLiner": ""
  },
  "timeline": [],
  "quotes": [],
  "faq": [],
  "hasLongform": false,
  "seo": {
    "noindex": true
  },
  "_deezer": {
    "fetchedAt": "2026-05-31T05:57:17.561Z",
    "source": "https://api.deezer.com/track/3504675271",
    "text": "Deezer ID: 3504675271\nNázev: AEZAKMI\nInterpret: Sakito\nÚčinkující: Sakito (Main), Vercetti CG (Main)\nAlbum: SPLITSCREEN\nVydáno: 2025-08-22\nDélka: 2:26 (146s)\nTrack #: 5\nDisk: 1\nGain: -10.5\nRank: 13225\nISRC: QZWDW2587333\nExplicit: ano\nOdkaz: https://www.deezer.com/track/3504675271\nPreview: https://cdnt-preview.dzcdn.net/api/1/1/a/b/c/0/abc8e426459bb896ffefeab091acfd91.mp3?hdnea=exp=1780207937~acl=/api/1/1/a/b/c/0/abc8e426459bb896ffefeab091acfd91.mp3*~data=user_id=0,application_id=42~hmac=322a8efdc027516c2d3bd7643213c6744bcd13bbd12c33e68bea89214ee6a692\nDostupnost: 214 zemí",
    "raw": {
      "id": 3504675271,
      "readable": true,
      "title": "AEZAKMI",
      "title_short": "AEZAKMI",
      "title_version": "",
      "isrc": "QZWDW2587333",
      "link": "https://www.deezer.com/track/3504675271",
      "share": "https://www.deezer.com/track/3504675271?utm_source=deezer&utm_content=track-3504675271&utm_term=0_1780207037&utm_medium=web",
      "duration": 146,
      "track_position": 5,
      "disk_number": 1,
      "rank": 13225,
      "release_date": "2025-08-22",
      "explicit_lyrics": true,
      "explicit_content_lyrics": 1,
      "explicit_content_cover": 2,
      "preview": "https://cdnt-preview.dzcdn.net/api/1/1/a/b/c/0/abc8e426459bb896ffefeab091acfd91.mp3?hdnea=exp=1780207937~acl=/api/1/1/a/b/c/0/abc8e426459bb896ffefeab091acfd91.mp3*~data=user_id=0,application_id=42~hmac=322a8efdc027516c2d3bd7643213c6744bcd13bbd12c33e68bea89214ee6a692",
      "bpm": 0,
      "gain": -10.5,
      "available_countries": [
        "AE",
        "AF",
        "AG",
        "AI",
        "AL",
        "AM",
        "AO",
        "AQ",
        "AR",
        "AS",
        "AT",
        "AU",
        "AZ",
        "BA",
        "BB",
        "BD",
        "BE",
        "BF",
        "BG",
        "BH",
        "BI",
        "BJ",
        "BN",
        "BO",
        "BQ",
        "BR",
        "BT",
        "BV",
        "BW",
        "BY",
        "CA",
        "CC",
        "CD",
        "CF",
        "CG",
        "CH",
        "CI",
        "CK",
        "CL",
        "CM",
        "CN",
        "CO",
        "CR",
        "CU",
        "CV",
        "CW",
        "CX",
        "CY",
        "CZ",
        "DE",
        "DJ",
        "DK",
        "DM",
        "DO",
        "DZ",
        "EC",
        "EE",
        "EG",
        "EH",
        "ER",
        "ES",
        "ET",
        "FI",
        "FJ",
        "FK",
        "FM",
        "FR",
        "GA",
        "GB",
        "GD",
        "GE",
        "GH",
        "GM",
        "GN",
        "GQ",
        "GR",
        "GS",
        "GT",
        "GU",
        "GW",
        "HK",
        "HM",
        "HN",
        "HR",
        "HU",
        "ID",
        "IE",
        "IL",
        "IN",
        "IO",
        "IQ",
        "IR",
        "IS",
        "IT",
        "JM",
        "JO",
        "JP",
        "KE",
        "KG",
        "KH",
        "KI",
        "KM",
        "KN",
        "KP",
        "KR",
        "KW",
        "KY",
        "KZ",
        "LA",
        "LB",
        "LC",
        "LK",
        "LR",
        "LS",
        "LT",
        "LU",
        "LV",
        "LY",
        "MA",
        "MD",
        "ME",
        "MG",
        "MH",
        "MK",
        "ML",
        "MM",
        "MN",
        "MP",
        "MR",
        "MS",
        "MT",
        "MU",
        "MV",
        "MW",
        "MX",
        "MY",
        "MZ",
        "NA",
        "NE",
        "NF",
        "NG",
        "NI",
        "NL",
        "NO",
        "NP",
        "NR",
        "NU",
        "NZ",
        "OM",
        "PA",
        "PE",
        "PG",
        "PH",
        "PK",
        "PL",
        "PN",
        "PS",
        "PT",
        "PW",
        "PY",
        "QA",
        "RO",
        "RS",
        "RU",
        "RW",
        "SA",
        "SB",
        "SC",
        "SD",
        "SE",
        "SG",
        "SI",
        "SJ",
        "SK",
        "SL",
        "SN",
        "SO",
        "SS",
        "ST",
        "SV",
        "SX",
        "SY",
        "SZ",
        "TC",
        "TD",
        "TG",
        "TH",
        "TJ",
        "TK",
        "TL",
        "TM",
        "TN",
        "TO",
        "TR",
        "TV",
        "TW",
        "TZ",
        "UA",
        "UG",
        "UM",
        "US",
        "UY",
        "UZ",
        "VC",
        "VE",
        "VG",
        "VI",
        "VN",
        "VU",
        "WS",
        "YE",
        "ZA",
        "ZM",
        "ZW"
      ],
      "contributors": [
        {
          "id": 1681291,
          "name": "Sakito",
          "link": "https://www.deezer.com/artist/1681291",
          "share": "https://www.deezer.com/artist/1681291?utm_source=deezer&utm_content=artist-1681291&utm_term=0_1780207037&utm_medium=web",
          "picture": "https://api.deezer.com/artist/1681291/image",
          "picture_small": "https://cdn-images.dzcdn.net/images/artist/e07447274efc6224996c13da677e762f/56x56-000000-80-0-0.jpg",
          "picture_medium": "https://cdn-images.dzcdn.net/images/artist/e07447274efc6224996c13da677e762f/250x250-000000-80-0-0.jpg",
          "picture_big": "https://cdn-images.dzcdn.net/images/artist/e07447274efc6224996c13da677e762f/500x500-000000-80-0-0.jpg",
          "picture_xl": "https://cdn-images.dzcdn.net/images/artist/e07447274efc6224996c13da677e762f/1000x1000-000000-80-0-0.jpg",
          "radio": true,
          "tracklist": "https://api.deezer.com/artist/1681291/top?limit=50",
          "type": "artist",
          "role": "Main"
        },
        {
          "id": 86746672,
          "name": "Vercetti CG",
          "link": "https://www.deezer.com/artist/86746672",
          "share": "https://www.deezer.com/artist/86746672?utm_source=deezer&utm_content=artist-86746672&utm_term=0_1780207037&utm_medium=web",
          "picture": "https://api.deezer.com/artist/86746672/image",
          "picture_small": "https://cdn-images.dzcdn.net/images/artist/7cd2bec50cd94c5c22a4ab56ae53d9f0/56x56-000000-80-0-0.jpg",
          "picture_medium": "https://cdn-images.dzcdn.net/images/artist/7cd2bec50cd94c5c22a4ab56ae53d9f0/250x250-000000-80-0-0.jpg",
          "picture_big": "https://cdn-images.dzcdn.net/images/artist/7cd2bec50cd94c5c22a4ab56ae53d9f0/500x500-000000-80-0-0.jpg",
          "picture_xl": "https://cdn-images.dzcdn.net/images/artist/7cd2bec50cd94c5c22a4ab56ae53d9f0/1000x1000-000000-80-0-0.jpg",
          "radio": true,
          "tracklist": "https://api.deezer.com/artist/86746672/top?limit=50",
          "type": "artist",
          "role": "Main"
        }
      ],
      "md5_image": "ec8e31ca9d74f5467d0b0f76a868a7d9",
      "track_token": "AAAAAWobzb1qHOb90eRVnon90SGT3VF6xrOTIA-Zy8IVNzaZc34AXTz8ezfXhUSRjyc5AYb5jdJNP1dH-UID0_DXH0-lmG3plEIcgcQ-pa0odHWi6XDJEh5vlfCIF3Tzu0E2GmrwXB_5zttdKcU7VCKTxheqqRDA6P8aE8mxDdPK8xkC7AE0m0-kT5H5YVYUCykjAqPKYzNSEithj5vmaxuGJb6kfhv29SXwUtZhNd1x_NqTW4kv7PzYwQaK0gb_2luTqTdQ4CIarLXn9jrsRb2zC0MC1ybLRU-CEn3CdxPa-MiYK1jqpUQaZjkRzENkgvIBT-0yDLMGR_fw0SBG-K_nEEDcHk8YPxZZrJUrbOi1nAUb0mQL_IVLqSFuIW4-f6wt6hqT",
      "artist": {
        "id": 1681291,
        "name": "Sakito",
        "link": "https://www.deezer.com/artist/1681291",
        "share": "https://www.deezer.com/artist/1681291?utm_source=deezer&utm_content=artist-1681291&utm_term=0_1780207037&utm_medium=web",
        "picture": "https://api.deezer.com/artist/1681291/image",
        "picture_small": "https://cdn-images.dzcdn.net/images/artist/e07447274efc6224996c13da677e762f/56x56-000000-80-0-0.jpg",
        "picture_medium": "https://cdn-images.dzcdn.net/images/artist/e07447274efc6224996c13da677e762f/250x250-000000-80-0-0.jpg",
        "picture_big": "https://cdn-images.dzcdn.net/images/artist/e07447274efc6224996c13da677e762f/500x500-000000-80-0-0.jpg",
        "picture_xl": "https://cdn-images.dzcdn.net/images/artist/e07447274efc6224996c13da677e762f/1000x1000-000000-80-0-0.jpg",
        "radio": true,
        "tracklist": "https://api.deezer.com/artist/1681291/top?limit=50",
        "type": "artist"
      },
      "album": {
        "id": 803485161,
        "title": "SPLITSCREEN",
        "link": "https://www.deezer.com/album/803485161",
        "cover": "https://api.deezer.com/album/803485161/image",
        "cover_small": "https://cdn-images.dzcdn.net/images/cover/ec8e31ca9d74f5467d0b0f76a868a7d9/56x56-000000-80-0-0.jpg",
        "cover_medium": "https://cdn-images.dzcdn.net/images/cover/ec8e31ca9d74f5467d0b0f76a868a7d9/250x250-000000-80-0-0.jpg",
        "cover_big": "https://cdn-images.dzcdn.net/images/cover/ec8e31ca9d74f5467d0b0f76a868a7d9/500x500-000000-80-0-0.jpg",
        "cover_xl": "https://cdn-images.dzcdn.net/images/cover/ec8e31ca9d74f5467d0b0f76a868a7d9/1000x1000-000000-80-0-0.jpg",
        "md5_image": "ec8e31ca9d74f5467d0b0f76a868a7d9",
        "release_date": "2025-08-22",
        "tracklist": "https://api.deezer.com/album/803485161/tracks",
        "type": "album"
      },
      "type": "track"
    }
  }
}
