{
  "title": "UZI",
  "slug": "uzi",
  "rapper": "Jerry Lee",
  "rapperSlug": "jerry-lee",
  "label": "Hitmakerz Squad",
  "year": 2021,
  "genre": [],
  "description": "Jerry Lee v roce 2021 vydal singl. Obsahuje celkem jednu skladbu. Deska vyšla pod labelem Hitmakerz Squad.",
  "image": "https://cdn-images.dzcdn.net/images/cover/47675d3685523f392293b9134965757c/1000x1000-000000-80-0-0.jpg",
  "featured": false,
  "tracklist": [
    "UZI"
  ],
  "publishedAt": "2026-06-04T00:00:00.000Z",
  "releaseType": "single",
  "explicit": false,
  "body": {
    "raw": "\n## O albu\n\n[Jerry Lee](/raperi/jerry-lee) v roce 2021 vydal singl.\n\nAlbum obsahuje celkem jednu skladbu.\n\nDeska vyšla pod labelem Hitmakerz Squad.\n",
    "code": "var Component=(()=>{var m=Object.create;var l=Object.defineProperty;var p=Object.getOwnPropertyDescriptor;var h=Object.getOwnPropertyNames;var g=Object.getPrototypeOf,j=Object.prototype.hasOwnProperty;var y=(r,e)=>()=>(e||r((e={exports:{}}).exports,e),e.exports),b=(r,e)=>{for(var a in e)l(r,a,{get:e[a],enumerable:!0})},i=(r,e,a,s)=>{if(e&&typeof e==\"object\"||typeof e==\"function\")for(let t of h(e))!j.call(r,t)&&t!==a&&l(r,t,{get:()=>e[t],enumerable:!(s=p(e,t))||s.enumerable});return r};var k=(r,e,a)=>(a=r!=null?m(g(r)):{},i(e||!r||!r.__esModule?l(a,\"default\",{value:r,enumerable:!0}):a,r)),x=r=>i(l({},\"__esModule\",{value:!0}),r);var d=y((z,c)=>{c.exports=_jsx_runtime});var v={};b(v,{default:()=>u,frontmatter:()=>f});var n=k(d()),f={title:\"UZI\",slug:\"uzi\",rapper:\"Jerry Lee\",rapperSlug:\"jerry-lee\",label:\"Hitmakerz Squad\",year:2021,releaseType:\"single\",genre:[],description:\"Jerry Lee v roce 2021 vydal singl. Obsahuje celkem jednu skladbu. Deska vy\\u0161la pod labelem Hitmakerz Squad.\",image:\"https://cdn-images.dzcdn.net/images/cover/47675d3685523f392293b9134965757c/1000x1000-000000-80-0-0.jpg\",tracklist:[\"UZI\"],publishedAt:\"2026-06-04\"};function o(r){let e={a:\"a\",h2:\"h2\",p:\"p\",...r.components};return(0,n.jsxs)(n.Fragment,{children:[(0,n.jsx)(e.h2,{children:\"O albu\"}),`\n`,(0,n.jsxs)(e.p,{children:[(0,n.jsx)(e.a,{href:\"/raperi/jerry-lee\",children:\"Jerry Lee\"}),\" v roce 2021 vydal singl.\"]}),`\n`,(0,n.jsx)(e.p,{children:\"Album obsahuje celkem jednu skladbu.\"}),`\n`,(0,n.jsx)(e.p,{children:\"Deska vy\\u0161la pod labelem Hitmakerz Squad.\"})]})}function u(r={}){let{wrapper:e}=r.components||{};return e?(0,n.jsx)(e,{...r,children:(0,n.jsx)(o,{...r})}):o(r)}return x(v);})();\n;return Component;"
  },
  "_id": "alba/uzi.mdx",
  "_raw": {
    "sourceFilePath": "alba/uzi.mdx",
    "sourceFileName": "uzi.mdx",
    "sourceFileDir": "alba",
    "contentType": "mdx",
    "flattenedPath": "alba/uzi"
  },
  "type": "Album",
  "url": "/alba/uzi",
  "canonicalUrl": "https://4rap.cz/alba/uzi"
}