{
  "title": "Last Call (feat. Treez Lowkey)",
  "slug": "last-call-feat-treez-lowkey",
  "rapper": "Bobby Blaze",
  "rapperSlug": "bobby-blaze",
  "label": "Team Green",
  "year": 2018,
  "genre": [],
  "description": "Last Call (feat. Treez Lowkey) — singl od Bobby Blaze (2018).",
  "image": "https://cdn-images.dzcdn.net/images/cover/51fc3a0aa7eb7a6ef3b57f106e140027/1000x1000-000000-80-0-0.jpg",
  "tracklist": [
    "Last Call (feat. Treez Lowkey)"
  ],
  "publishedAt": "2026-06-04T00:00:00.000Z",
  "body": {
    "raw": "\n## O albu\n\n_Stub — doplnit._\n",
    "code": "var Component=(()=>{var b=Object.create;var l=Object.defineProperty;var d=Object.getOwnPropertyDescriptor;var f=Object.getOwnPropertyNames;var u=Object.getPrototypeOf,g=Object.prototype.hasOwnProperty;var h=(e,t)=>()=>(t||e((t={exports:{}}).exports,t),t.exports),x=(e,t)=>{for(var n in t)l(e,n,{get:t[n],enumerable:!0})},s=(e,t,n,o)=>{if(t&&typeof t==\"object\"||typeof t==\"function\")for(let r of f(t))!g.call(e,r)&&r!==n&&l(e,r,{get:()=>t[r],enumerable:!(o=d(t,r))||o.enumerable});return e};var y=(e,t,n)=>(n=e!=null?b(u(e)):{},s(t||!e||!e.__esModule?l(n,\"default\",{value:e,enumerable:!0}):n,e)),z=e=>s(l({},\"__esModule\",{value:!0}),e);var i=h((k,c)=>{c.exports=_jsx_runtime});var _={};x(_,{default:()=>p,frontmatter:()=>L});var a=y(i()),L={title:\"Last Call (feat. Treez Lowkey)\",slug:\"last-call-feat-treez-lowkey\",rapper:\"Bobby Blaze\",rapperSlug:\"bobby-blaze\",label:\"Team Green\",year:2018,genre:[],description:\"Last Call (feat. Treez Lowkey) \\u2014 singl od Bobby Blaze (2018).\",image:\"https://cdn-images.dzcdn.net/images/cover/51fc3a0aa7eb7a6ef3b57f106e140027/1000x1000-000000-80-0-0.jpg\",tracklist:[\"Last Call (feat. Treez Lowkey)\"],publishedAt:\"2026-06-04\"};function m(e){let t={em:\"em\",h2:\"h2\",p:\"p\",...e.components};return(0,a.jsxs)(a.Fragment,{children:[(0,a.jsx)(t.h2,{children:\"O albu\"}),`\n`,(0,a.jsx)(t.p,{children:(0,a.jsx)(t.em,{children:\"Stub \\u2014 doplnit.\"})})]})}function p(e={}){let{wrapper:t}=e.components||{};return t?(0,a.jsx)(t,{...e,children:(0,a.jsx)(m,{...e})}):m(e)}return z(_);})();\n;return Component;"
  },
  "_id": "alba/last-call-feat-treez-lowkey.mdx",
  "_raw": {
    "sourceFilePath": "alba/last-call-feat-treez-lowkey.mdx",
    "sourceFileName": "last-call-feat-treez-lowkey.mdx",
    "sourceFileDir": "alba",
    "contentType": "mdx",
    "flattenedPath": "alba/last-call-feat-treez-lowkey"
  },
  "type": "Album",
  "url": "/alba/last-call-feat-treez-lowkey",
  "canonicalUrl": "https://4rap.cz/alba/last-call-feat-treez-lowkey"
}