{
  "title": "Drag4Hard",
  "slug": "drag4hard",
  "rapper": "Maniak",
  "rapperSlug": "maniak",
  "label": "JOG",
  "year": 2023,
  "genre": [],
  "description": "Drag4Hard — EP od Maniak (2023).",
  "image": "https://cdn-images.dzcdn.net/images/cover/92cc9b60c7e14cbb13522c81971a74bc/1000x1000-000000-80-0-0.jpg",
  "featured": false,
  "tracklist": [
    "#1Threat",
    "Smackin",
    "Middle Man",
    "Try"
  ],
  "publishedAt": "2026-06-04T00:00:00.000Z",
  "body": {
    "raw": "\n## O albu\n\n_Stub — doplnit._\n",
    "code": "var Component=(()=>{var p=Object.create;var c=Object.defineProperty;var g=Object.getOwnPropertyDescriptor;var h=Object.getOwnPropertyNames;var u=Object.getPrototypeOf,x=Object.prototype.hasOwnProperty;var b=(e,n)=>()=>(n||e((n={exports:{}}).exports,n),n.exports),M=(e,n)=>{for(var r in n)c(e,r,{get:n[r],enumerable:!0})},o=(e,n,r,i)=>{if(n&&typeof n==\"object\"||typeof n==\"function\")for(let a of h(n))!x.call(e,a)&&a!==r&&c(e,a,{get:()=>n[a],enumerable:!(i=g(n,a))||i.enumerable});return e};var _=(e,n,r)=>(r=e!=null?p(u(e)):{},o(n||!e||!e.__esModule?c(r,\"default\",{value:e,enumerable:!0}):r,e)),j=e=>o(c({},\"__esModule\",{value:!0}),e);var d=b((y,s)=>{s.exports=_jsx_runtime});var k={};M(k,{default:()=>l,frontmatter:()=>f});var t=_(d()),f={title:\"Drag4Hard\",slug:\"drag4hard\",rapper:\"Maniak\",rapperSlug:\"maniak\",label:\"JOG\",year:2023,genre:[],description:\"Drag4Hard \\u2014 EP od Maniak (2023).\",image:\"https://cdn-images.dzcdn.net/images/cover/92cc9b60c7e14cbb13522c81971a74bc/1000x1000-000000-80-0-0.jpg\",tracklist:[\"#1Threat\",\"Smackin\",\"Middle Man\",\"Try\"],publishedAt:\"2026-06-04\"};function m(e){let n={em:\"em\",h2:\"h2\",p:\"p\",...e.components};return(0,t.jsxs)(t.Fragment,{children:[(0,t.jsx)(n.h2,{children:\"O albu\"}),`\n`,(0,t.jsx)(n.p,{children:(0,t.jsx)(n.em,{children:\"Stub \\u2014 doplnit.\"})})]})}function l(e={}){let{wrapper:n}=e.components||{};return n?(0,t.jsx)(n,{...e,children:(0,t.jsx)(m,{...e})}):m(e)}return j(k);})();\n;return Component;"
  },
  "_id": "alba/drag4hard.mdx",
  "_raw": {
    "sourceFilePath": "alba/drag4hard.mdx",
    "sourceFileName": "drag4hard.mdx",
    "sourceFileDir": "alba",
    "contentType": "mdx",
    "flattenedPath": "alba/drag4hard"
  },
  "type": "Album",
  "url": "/alba/drag4hard",
  "canonicalUrl": "https://4rap.cz/alba/drag4hard"
}