{
  "id": "track_pil-c-nestaram-sa",
  "type": "track",
  "slug": "pil-c-nestaram-sa",
  "title": "NESTARAM SA",
  "description": "Skladba je manifestem osobní nezávislosti, ve kterém Pil C deklaruje naprostý nezájem o názory okolí, sociální statusy a kritiku svého úspěchu.",
  "publishedAt": "2024-01-01",
  "extraMeta": {
    "duration": null,
    "explicit": true,
    "sources": [
      "https://open.spotify.com/track/4C5A5l88M2Z9M8G9eG6Y6I",
      "https://www.youtube.com/watch?v=R2_E-n-N2n8"
    ]
  },
  "youtube": {
    "id": "R2_E-n-N2n8",
    "title": "NESTARAM SA",
    "channel": "",
    "views": 0,
    "uploadDate": "2024-01-01",
    "isOfficial": false,
    "isLyricVideo": false,
    "isLive": false
  }
}
