{
  "title": "Avec Moi (Kevin McKay Remix)",
  "slug": "avec-moi-kevin-mckay-remix",
  "rapper": "James Cole",
  "rapperSlug": "james-cole",
  "year": 2023,
  "description": "Avec Moi (Kevin McKay Remix) — singl od James Cole (2023).",
  "image": "https://cdn-images.dzcdn.net/images/cover/75590600594887454359bb3c18901ad3/1000x1000-000000-80-0-0.jpg",
  "publishedAt": "2026-06-04T00:00:00.000Z",
  "releaseType": "single",
  "explicit": false,
  "releaseDate": "2026-06-04T00:00:00.000Z",
  "body": {
    "raw": "\n**[Avec Moi (Kevin McKay Remix)](/skladby/avec-moi-kevin-mckay-remix)** od [James Cole](/raperi/james-cole) (2023).\n",
    "code": "var Component=(()=>{var d=Object.create;var r=Object.defineProperty;var x=Object.getOwnPropertyDescriptor;var g=Object.getOwnPropertyNames;var v=Object.getPrototypeOf,u=Object.prototype.hasOwnProperty;var h=(n,e)=>()=>(e||n((e={exports:{}}).exports,e),e.exports),y=(n,e)=>{for(var t in e)r(n,t,{get:e[t],enumerable:!0})},s=(n,e,t,o)=>{if(e&&typeof e==\"object\"||typeof e==\"function\")for(let i of g(e))!u.call(n,i)&&i!==t&&r(n,i,{get:()=>e[i],enumerable:!(o=x(e,i))||o.enumerable});return n};var M=(n,e,t)=>(t=n!=null?d(v(n)):{},s(e||!n||!n.__esModule?r(t,\"default\",{value:n,enumerable:!0}):t,n)),f=n=>s(r({},\"__esModule\",{value:!0}),n);var m=h((k,c)=>{c.exports=_jsx_runtime});var K={};y(K,{default:()=>p,frontmatter:()=>j});var a=M(m()),j={title:\"Avec Moi (Kevin McKay Remix)\",slug:\"avec-moi-kevin-mckay-remix\",rapper:\"James Cole\",rapperSlug:\"james-cole\",year:2023,description:\"Avec Moi (Kevin McKay Remix) \\u2014 singl od James Cole (2023).\",image:\"https://cdn-images.dzcdn.net/images/cover/75590600594887454359bb3c18901ad3/1000x1000-000000-80-0-0.jpg\",publishedAt:\"2026-06-04\",releaseType:\"single\",explicit:!1,releaseDate:\"2026-06-04\"};function l(n){let e={a:\"a\",p:\"p\",strong:\"strong\",...n.components};return(0,a.jsxs)(e.p,{children:[(0,a.jsx)(e.strong,{children:(0,a.jsx)(e.a,{href:\"/skladby/avec-moi-kevin-mckay-remix\",children:\"Avec Moi (Kevin McKay Remix)\"})}),\" od \",(0,a.jsx)(e.a,{href:\"/raperi/james-cole\",children:\"James Cole\"}),\" (2023).\"]})}function p(n={}){let{wrapper:e}=n.components||{};return e?(0,a.jsx)(e,{...n,children:(0,a.jsx)(l,{...n})}):l(n)}return f(K);})();\n;return Component;"
  },
  "_id": "skladby/avec-moi-kevin-mckay-remix.mdx",
  "_raw": {
    "sourceFilePath": "skladby/avec-moi-kevin-mckay-remix.mdx",
    "sourceFileName": "avec-moi-kevin-mckay-remix.mdx",
    "sourceFileDir": "skladby",
    "contentType": "mdx",
    "flattenedPath": "skladby/avec-moi-kevin-mckay-remix"
  },
  "type": "Skladba",
  "url": "/skladby/avec-moi-kevin-mckay-remix",
  "canonicalUrl": "https://4rap.cz/skladby/avec-moi-kevin-mckay-remix"
}