{
  "title": "Bez faktury",
  "slug": "bez-faktury-dj-fatte",
  "rapper": "DJ Fatte",
  "rapperSlug": "dj-fatte",
  "features": [
    "johnyboss",
    "kato"
  ],
  "featuresNames": [
    "JOHNYBOSS",
    "Kato"
  ],
  "album": "Reflex",
  "albumSlug": "reflex",
  "year": 2022,
  "genre": [
    ""
  ],
  "duration": "4:15",
  "trackNumber": 11,
  "producers": [],
  "producersNames": [],
  "description": "Bez faktury — skladba od DJ Fatte.",
  "publishedAt": "2026-06-04T00:00:00.000Z",
  "explicit": false,
  "body": {
    "raw": "\n**[Bez faktury](/skladby/bez-faktury-dj-fatte)** od [DJ Fatte](/raperi/dj-fatte) z alba [Reflex](/alba/reflex) (2022).\n",
    "code": "var Component=(()=>{var i=Object.create;var o=Object.defineProperty;var p=Object.getOwnPropertyDescriptor;var x=Object.getOwnPropertyNames;var m=Object.getPrototypeOf,b=Object.prototype.hasOwnProperty;var h=(t,e)=>()=>(e||t((e={exports:{}}).exports,e),e.exports),j=(t,e)=>{for(var a in e)o(t,a,{get:e[a],enumerable:!0})},u=(t,e,a,s)=>{if(e&&typeof e==\"object\"||typeof e==\"function\")for(let n of x(e))!b.call(t,n)&&n!==a&&o(t,n,{get:()=>e[n],enumerable:!(s=p(e,n))||s.enumerable});return t};var k=(t,e,a)=>(a=t!=null?i(m(t)):{},u(e||!t||!t.__esModule?o(a,\"default\",{value:t,enumerable:!0}):a,t)),y=t=>u(o({},\"__esModule\",{value:!0}),t);var l=h((D,f)=>{f.exports=_jsx_runtime});var z={};j(z,{default:()=>c,frontmatter:()=>g});var r=k(l()),g={title:\"Bez faktury\",slug:\"bez-faktury-dj-fatte\",rapper:\"DJ Fatte\",rapperSlug:\"dj-fatte\",features:[\"johnyboss\",\"kato\"],featuresNames:[\"JOHNYBOSS\",\"Kato\"],album:\"Reflex\",albumSlug:\"reflex\",year:2022,genre:[\"\"],duration:\"4:15\",trackNumber:11,producers:[],producersNames:[],description:\"Bez faktury \\u2014 skladba od DJ Fatte.\",publishedAt:\"2026-06-04\"};function d(t){let e={a:\"a\",p:\"p\",strong:\"strong\",...t.components};return(0,r.jsxs)(e.p,{children:[(0,r.jsx)(e.strong,{children:(0,r.jsx)(e.a,{href:\"/skladby/bez-faktury-dj-fatte\",children:\"Bez faktury\"})}),\" od \",(0,r.jsx)(e.a,{href:\"/raperi/dj-fatte\",children:\"DJ Fatte\"}),\" z alba \",(0,r.jsx)(e.a,{href:\"/alba/reflex\",children:\"Reflex\"}),\" (2022).\"]})}function c(t={}){let{wrapper:e}=t.components||{};return e?(0,r.jsx)(e,{...t,children:(0,r.jsx)(d,{...t})}):d(t)}return y(z);})();\n;return Component;"
  },
  "_id": "skladby/bez-faktury-dj-fatte.mdx",
  "_raw": {
    "sourceFilePath": "skladby/bez-faktury-dj-fatte.mdx",
    "sourceFileName": "bez-faktury-dj-fatte.mdx",
    "sourceFileDir": "skladby",
    "contentType": "mdx",
    "flattenedPath": "skladby/bez-faktury-dj-fatte"
  },
  "type": "Skladba",
  "url": "/skladby/bez-faktury-dj-fatte",
  "canonicalUrl": "https://4rap.cz/skladby/bez-faktury-dj-fatte"
}