{
  "title": "Nagano",
  "slug": "nagano-yzomandias",
  "rapper": "Yzomandias",
  "rapperSlug": "yzomandias",
  "features": [
    "robin-zoot"
  ],
  "featuresNames": [
    "Robin Zoot"
  ],
  "album": "J. Eden",
  "albumSlug": "j-eden",
  "year": 2020,
  "genre": [
    ""
  ],
  "duration": "1:51",
  "trackNumber": 19,
  "producers": [],
  "producersNames": [],
  "description": "Nagano — skladba od Yzomandias.",
  "publishedAt": "2026-05-31T00:00:00.000Z",
  "explicit": false,
  "body": {
    "raw": "\n**[Nagano](/skladby/nagano-yzomandias)** od [Yzomandias](/raperi/yzomandias) z alba [J. EDEN](/alba/j-eden) (2020).\n",
    "code": "var Component=(()=>{var l=Object.create;var t=Object.defineProperty;var p=Object.getOwnPropertyDescriptor;var g=Object.getOwnPropertyNames;var b=Object.getPrototypeOf,f=Object.prototype.hasOwnProperty;var h=(n,a)=>()=>(a||n((a={exports:{}}).exports,a),a.exports),x=(n,a)=>{for(var o in a)t(n,o,{get:a[o],enumerable:!0})},d=(n,a,o,s)=>{if(a&&typeof a==\"object\"||typeof a==\"function\")for(let r of g(a))!f.call(n,r)&&r!==o&&t(n,r,{get:()=>a[r],enumerable:!(s=p(a,r))||s.enumerable});return n};var z=(n,a,o)=>(o=n!=null?l(b(n)):{},d(a||!n||!n.__esModule?t(o,\"default\",{value:n,enumerable:!0}):o,n)),j=n=>d(t({},\"__esModule\",{value:!0}),n);var c=h((k,i)=>{i.exports=_jsx_runtime});var N={};x(N,{default:()=>u,frontmatter:()=>y});var e=z(c()),y={title:\"Nagano\",slug:\"nagano-yzomandias\",rapper:\"Yzomandias\",rapperSlug:\"yzomandias\",features:[\"robin-zoot\"],featuresNames:[\"Robin Zoot\"],album:\"J. Eden\",albumSlug:\"j-eden\",year:2020,genre:[\"\"],duration:\"1:51\",trackNumber:19,producers:[],producersNames:[],description:\"Nagano \\u2014 skladba od Yzomandias.\",publishedAt:\"2026-05-31\"};function m(n){let a={a:\"a\",p:\"p\",strong:\"strong\",...n.components};return(0,e.jsxs)(a.p,{children:[(0,e.jsx)(a.strong,{children:(0,e.jsx)(a.a,{href:\"/skladby/nagano-yzomandias\",children:\"Nagano\"})}),\" od \",(0,e.jsx)(a.a,{href:\"/raperi/yzomandias\",children:\"Yzomandias\"}),\" z alba \",(0,e.jsx)(a.a,{href:\"/alba/j-eden\",children:\"J. EDEN\"}),\" (2020).\"]})}function u(n={}){let{wrapper:a}=n.components||{};return a?(0,e.jsx)(a,{...n,children:(0,e.jsx)(m,{...n})}):m(n)}return j(N);})();\n;return Component;"
  },
  "_id": "skladby/nagano-yzomandias.mdx",
  "_raw": {
    "sourceFilePath": "skladby/nagano-yzomandias.mdx",
    "sourceFileName": "nagano-yzomandias.mdx",
    "sourceFileDir": "skladby",
    "contentType": "mdx",
    "flattenedPath": "skladby/nagano-yzomandias"
  },
  "type": "Skladba",
  "url": "/skladby/nagano-yzomandias",
  "canonicalUrl": "https://4rap.cz/skladby/nagano-yzomandias"
}