{
  "title": "BANG BANG",
  "slug": "bang-bang",
  "rapper": "James Cole",
  "rapperSlug": "james-cole",
  "year": 2023,
  "description": "BANG BANG — singl od James Cole (2023).",
  "image": "https://cdn-images.dzcdn.net/images/cover/35439b57792da448c099c982a308a99d/1000x1000-000000-80-0-0.jpg",
  "publishedAt": "2026-06-04T00:00:00.000Z",
  "releaseType": "single",
  "explicit": false,
  "releaseDate": "2026-06-04T00:00:00.000Z",
  "body": {
    "raw": "\n**[BANG BANG](/skladby/bang-bang)** od [James Cole](/raperi/james-cole) (2023).\n",
    "code": "var Component=(()=>{var g=Object.create;var s=Object.defineProperty;var m=Object.getOwnPropertyDescriptor;var x=Object.getOwnPropertyNames;var u=Object.getPrototypeOf,h=Object.prototype.hasOwnProperty;var f=(n,e)=>()=>(e||n((e={exports:{}}).exports,e),e.exports),j=(n,e)=>{for(var t in e)s(n,t,{get:e[t],enumerable:!0})},c=(n,e,t,o)=>{if(e&&typeof e==\"object\"||typeof e==\"function\")for(let r of x(e))!h.call(n,r)&&r!==t&&s(n,r,{get:()=>e[r],enumerable:!(o=m(e,r))||o.enumerable});return n};var b=(n,e,t)=>(t=n!=null?g(u(n)):{},c(e||!n||!n.__esModule?s(t,\"default\",{value:n,enumerable:!0}):t,n)),A=n=>c(s({},\"__esModule\",{value:!0}),n);var i=f((_,l)=>{l.exports=_jsx_runtime});var G={};j(G,{default:()=>p,frontmatter:()=>B});var a=b(i()),B={title:\"BANG BANG\",slug:\"bang-bang\",rapper:\"James Cole\",rapperSlug:\"james-cole\",year:2023,description:\"BANG BANG \\u2014 singl od James Cole (2023).\",image:\"https://cdn-images.dzcdn.net/images/cover/35439b57792da448c099c982a308a99d/1000x1000-000000-80-0-0.jpg\",publishedAt:\"2026-06-04\",releaseType:\"single\",explicit:!1,releaseDate:\"2026-06-04\"};function d(n){let e={a:\"a\",p:\"p\",strong:\"strong\",...n.components};return(0,a.jsxs)(e.p,{children:[(0,a.jsx)(e.strong,{children:(0,a.jsx)(e.a,{href:\"/skladby/bang-bang\",children:\"BANG BANG\"})}),\" od \",(0,a.jsx)(e.a,{href:\"/raperi/james-cole\",children:\"James Cole\"}),\" (2023).\"]})}function p(n={}){let{wrapper:e}=n.components||{};return e?(0,a.jsx)(e,{...n,children:(0,a.jsx)(d,{...n})}):d(n)}return A(G);})();\n;return Component;"
  },
  "_id": "skladby/bang-bang.mdx",
  "_raw": {
    "sourceFilePath": "skladby/bang-bang.mdx",
    "sourceFileName": "bang-bang.mdx",
    "sourceFileDir": "skladby",
    "contentType": "mdx",
    "flattenedPath": "skladby/bang-bang"
  },
  "type": "Skladba",
  "url": "/skladby/bang-bang",
  "canonicalUrl": "https://4rap.cz/skladby/bang-bang"
}