{
  "id": "track_english-mad-thing-man",
  "kind": "track",
  "slug": "english-mad-thing-man",
  "title": "English",
  "status": "stub",
  "createdAt": "2026-06-06",
  "updatedAt": "2026-06-06",
  "meta": {
    "primaryArtist": {
      "kind": "rapper",
      "slug": "mad-thing-man"
    },
    "features": [
      {
        "kind": "rapper",
        "slug": "peter-pann"
      },
      {
        "kind": "rapper",
        "slug": "3gga"
      },
      {
        "kind": "rapper",
        "slug": "t-i-p"
      }
    ],
    "album": {
      "kind": "album",
      "slug": "eu-got-talent-vol-1"
    },
    "producers": [],
    "year": 2025,
    "duration": "2:48",
    "trackNumber": 4,
    "genres": [],
    "deezerId": 3720766582,
    "isrc": "QZYFZ2550352",
    "explicit": false,
    "cover": "https://cdn-images.dzcdn.net/images/cover/967385d9226a851b283c921803039a6a/1000x1000-000000-80-0-0.jpg",
    "previewUrl": "https://cdnt-preview.dzcdn.net/api/1/1/7/9/e/0/79ede4eea7c25776c19eed75f15c97fd.mp3?hdnea=exp=1780747706~acl=/api/1/1/7/9/e/0/79ede4eea7c25776c19eed75f15c97fd.mp3*~data=user_id=0,application_id=42~hmac=7ceca8a4e0bc464df01a919fd755f9b8286a5f4b824f09b8965102bd5c5cbb95"
  },
  "_deezer": {
    "fetchedAt": "2026-06-06T11:53:26.723Z",
    "raw": {
      "id": 3720766582,
      "readable": true,
      "title": "English",
      "title_short": "English",
      "title_version": "",
      "isrc": "QZYFZ2550352",
      "link": "https://www.deezer.com/track/3720766582",
      "share": "https://www.deezer.com/track/3720766582?utm_source=deezer&utm_content=track-3720766582&utm_term=0_1780746806&utm_medium=web",
      "duration": 168,
      "track_position": 4,
      "disk_number": 1,
      "rank": 37671,
      "release_date": "2025-12-31",
      "explicit_lyrics": false,
      "explicit_content_lyrics": 0,
      "explicit_content_cover": 2,
      "preview": "https://cdnt-preview.dzcdn.net/api/1/1/7/9/e/0/79ede4eea7c25776c19eed75f15c97fd.mp3?hdnea=exp=1780747706~acl=/api/1/1/7/9/e/0/79ede4eea7c25776c19eed75f15c97fd.mp3*~data=user_id=0,application_id=42~hmac=7ceca8a4e0bc464df01a919fd755f9b8286a5f4b824f09b8965102bd5c5cbb95",
      "bpm": 0,
      "gain": -8,
      "available_countries": [
        "AE",
        "AF",
        "AG",
        "AI",
        "AL",
        "AM",
        "AO",
        "AQ",
        "AR",
        "AS",
        "AT",
        "AU",
        "AZ",
        "BA",
        "BB",
        "BD",
        "BE",
        "BF",
        "BG",
        "BH",
        "BI",
        "BJ",
        "BN",
        "BO",
        "BQ",
        "BR",
        "BT",
        "BV",
        "BW",
        "BY",
        "CA",
        "CC",
        "CD",
        "CF",
        "CG",
        "CH",
        "CI",
        "CK",
        "CL",
        "CM",
        "CN",
        "CO",
        "CR",
        "CU",
        "CV",
        "CW",
        "CX",
        "CY",
        "CZ",
        "DE",
        "DJ",
        "DK",
        "DM",
        "DO",
        "DZ",
        "EC",
        "EE",
        "EG",
        "EH",
        "ER",
        "ES",
        "ET",
        "FI",
        "FJ",
        "FK",
        "FM",
        "FR",
        "GA",
        "GB",
        "GD",
        "GE",
        "GH",
        "GM",
        "GN",
        "GQ",
        "GR",
        "GS",
        "GT",
        "GU",
        "GW",
        "HK",
        "HM",
        "HN",
        "HR",
        "HU",
        "ID",
        "IE",
        "IL",
        "IN",
        "IO",
        "IQ",
        "IR",
        "IS",
        "IT",
        "JM",
        "JO",
        "JP",
        "KE",
        "KG",
        "KH",
        "KI",
        "KM",
        "KN",
        "KP",
        "KR",
        "KW",
        "KY",
        "KZ",
        "LA",
        "LB",
        "LC",
        "LK",
        "LR",
        "LS",
        "LT",
        "LU",
        "LV",
        "LY",
        "MA",
        "MD",
        "ME",
        "MG",
        "MH",
        "MK",
        "ML",
        "MM",
        "MN",
        "MP",
        "MR",
        "MS",
        "MT",
        "MU",
        "MV",
        "MW",
        "MX",
        "MY",
        "MZ",
        "NA",
        "NE",
        "NF",
        "NG",
        "NI",
        "NL",
        "NO",
        "NP",
        "NR",
        "NU",
        "NZ",
        "OM",
        "PA",
        "PE",
        "PG",
        "PH",
        "PK",
        "PL",
        "PN",
        "PS",
        "PT",
        "PW",
        "PY",
        "QA",
        "RO",
        "RS",
        "RU",
        "RW",
        "SA",
        "SB",
        "SC",
        "SD",
        "SE",
        "SG",
        "SI",
        "SJ",
        "SK",
        "SL",
        "SN",
        "SO",
        "SS",
        "ST",
        "SV",
        "SX",
        "SY",
        "SZ",
        "TC",
        "TD",
        "TG",
        "TH",
        "TJ",
        "TK",
        "TL",
        "TM",
        "TN",
        "TO",
        "TR",
        "TV",
        "TW",
        "TZ",
        "UA",
        "UG",
        "UM",
        "US",
        "UY",
        "UZ",
        "VC",
        "VE",
        "VG",
        "VI",
        "VN",
        "VU",
        "WS",
        "YE",
        "ZA",
        "ZM",
        "ZW"
      ],
      "contributors": [
        {
          "id": 362265742,
          "name": "Mad Thing Man",
          "link": "https://www.deezer.com/artist/362265742",
          "share": "https://www.deezer.com/artist/362265742?utm_source=deezer&utm_content=artist-362265742&utm_term=0_1780746806&utm_medium=web",
          "picture": "https://api.deezer.com/artist/362265742/image",
          "picture_small": "https://cdn-images.dzcdn.net/images/artist/967385d9226a851b283c921803039a6a/56x56-000000-80-0-0.jpg",
          "picture_medium": "https://cdn-images.dzcdn.net/images/artist/967385d9226a851b283c921803039a6a/250x250-000000-80-0-0.jpg",
          "picture_big": "https://cdn-images.dzcdn.net/images/artist/967385d9226a851b283c921803039a6a/500x500-000000-80-0-0.jpg",
          "picture_xl": "https://cdn-images.dzcdn.net/images/artist/967385d9226a851b283c921803039a6a/1000x1000-000000-80-0-0.jpg",
          "radio": true,
          "tracklist": "https://api.deezer.com/artist/362265742/top?limit=50",
          "type": "artist",
          "role": "Main"
        },
        {
          "id": 6549057,
          "name": "Peter Pann",
          "link": "https://www.deezer.com/artist/6549057",
          "share": "https://www.deezer.com/artist/6549057?utm_source=deezer&utm_content=artist-6549057&utm_term=0_1780746806&utm_medium=web",
          "picture": "https://api.deezer.com/artist/6549057/image",
          "picture_small": "https://cdn-images.dzcdn.net/images/artist/b2efdacb8b0fa3b167f845ac054e2f9b/56x56-000000-80-0-0.jpg",
          "picture_medium": "https://cdn-images.dzcdn.net/images/artist/b2efdacb8b0fa3b167f845ac054e2f9b/250x250-000000-80-0-0.jpg",
          "picture_big": "https://cdn-images.dzcdn.net/images/artist/b2efdacb8b0fa3b167f845ac054e2f9b/500x500-000000-80-0-0.jpg",
          "picture_xl": "https://cdn-images.dzcdn.net/images/artist/b2efdacb8b0fa3b167f845ac054e2f9b/1000x1000-000000-80-0-0.jpg",
          "radio": true,
          "tracklist": "https://api.deezer.com/artist/6549057/top?limit=50",
          "type": "artist",
          "role": "Main"
        },
        {
          "id": 275653,
          "name": "3gga",
          "link": "https://www.deezer.com/artist/275653",
          "share": "https://www.deezer.com/artist/275653?utm_source=deezer&utm_content=artist-275653&utm_term=0_1780746806&utm_medium=web",
          "picture": "https://api.deezer.com/artist/275653/image",
          "picture_small": "https://cdn-images.dzcdn.net/images/artist/36e8c183bf4163a918f2cbb758997b11/56x56-000000-80-0-0.jpg",
          "picture_medium": "https://cdn-images.dzcdn.net/images/artist/36e8c183bf4163a918f2cbb758997b11/250x250-000000-80-0-0.jpg",
          "picture_big": "https://cdn-images.dzcdn.net/images/artist/36e8c183bf4163a918f2cbb758997b11/500x500-000000-80-0-0.jpg",
          "picture_xl": "https://cdn-images.dzcdn.net/images/artist/36e8c183bf4163a918f2cbb758997b11/1000x1000-000000-80-0-0.jpg",
          "radio": true,
          "tracklist": "https://api.deezer.com/artist/275653/top?limit=50",
          "type": "artist",
          "role": "Main"
        },
        {
          "id": 103025,
          "name": "T.I.P",
          "link": "https://www.deezer.com/artist/103025",
          "share": "https://www.deezer.com/artist/103025?utm_source=deezer&utm_content=artist-103025&utm_term=0_1780746806&utm_medium=web",
          "picture": "https://api.deezer.com/artist/103025/image",
          "picture_small": "https://cdn-images.dzcdn.net/images/artist/17bc3dbc97b45849fb8ba1a94e37731a/56x56-000000-80-0-0.jpg",
          "picture_medium": "https://cdn-images.dzcdn.net/images/artist/17bc3dbc97b45849fb8ba1a94e37731a/250x250-000000-80-0-0.jpg",
          "picture_big": "https://cdn-images.dzcdn.net/images/artist/17bc3dbc97b45849fb8ba1a94e37731a/500x500-000000-80-0-0.jpg",
          "picture_xl": "https://cdn-images.dzcdn.net/images/artist/17bc3dbc97b45849fb8ba1a94e37731a/1000x1000-000000-80-0-0.jpg",
          "radio": true,
          "tracklist": "https://api.deezer.com/artist/103025/top?limit=50",
          "type": "artist",
          "role": "Featured"
        }
      ],
      "md5_image": "967385d9226a851b283c921803039a6a",
      "track_token": "AAAAAWokCjZqJSN22u7GTuozBeghMMj1XB0Rmqr8DO9uz2AtvpgDRbDkePdCRmBYJcgcV_QVQQyLwxoERo1d84V691KWmCgjJT_3rrswvNiEZpd6NHYNUgd7mckUFRp2ITXvdJpd0yRkOASqdD1cMf_bZFN4Z0V-YjV7oEr_vmGDC1JjEazl-_pBCiJOchGXla86rbu6oQNdUWrC6VX7G883_wbwVYJN4XAaxn_tUe7d_lJmU3vs4khIqOWoMbZY7DmzRFOoDRDmWyU4xNGMFZea7qLWkvdoG5EfIbmm3jbOKDlMfdciJwgWuSpipSYAz59ic3a6HpiX7p4AyJYkJrQdt3JiUdqWNjgDn7EakOWaZycZiuvA6cKg0pSk4u-ZmbeDauel",
      "artist": {
        "id": 362265742,
        "name": "Mad Thing Man",
        "link": "https://www.deezer.com/artist/362265742",
        "share": "https://www.deezer.com/artist/362265742?utm_source=deezer&utm_content=artist-362265742&utm_term=0_1780746806&utm_medium=web",
        "picture": "https://api.deezer.com/artist/362265742/image",
        "picture_small": "https://cdn-images.dzcdn.net/images/artist/967385d9226a851b283c921803039a6a/56x56-000000-80-0-0.jpg",
        "picture_medium": "https://cdn-images.dzcdn.net/images/artist/967385d9226a851b283c921803039a6a/250x250-000000-80-0-0.jpg",
        "picture_big": "https://cdn-images.dzcdn.net/images/artist/967385d9226a851b283c921803039a6a/500x500-000000-80-0-0.jpg",
        "picture_xl": "https://cdn-images.dzcdn.net/images/artist/967385d9226a851b283c921803039a6a/1000x1000-000000-80-0-0.jpg",
        "radio": true,
        "tracklist": "https://api.deezer.com/artist/362265742/top?limit=50",
        "type": "artist"
      },
      "album": {
        "id": 878852082,
        "title": "EU Got Talent Vol.1",
        "link": "https://www.deezer.com/album/878852082",
        "cover": "https://api.deezer.com/album/878852082/image",
        "cover_small": "https://cdn-images.dzcdn.net/images/cover/967385d9226a851b283c921803039a6a/56x56-000000-80-0-0.jpg",
        "cover_medium": "https://cdn-images.dzcdn.net/images/cover/967385d9226a851b283c921803039a6a/250x250-000000-80-0-0.jpg",
        "cover_big": "https://cdn-images.dzcdn.net/images/cover/967385d9226a851b283c921803039a6a/500x500-000000-80-0-0.jpg",
        "cover_xl": "https://cdn-images.dzcdn.net/images/cover/967385d9226a851b283c921803039a6a/1000x1000-000000-80-0-0.jpg",
        "md5_image": "967385d9226a851b283c921803039a6a",
        "release_date": "2025-12-31",
        "tracklist": "https://api.deezer.com/album/878852082/tracks",
        "type": "album"
      },
      "type": "track"
    }
  }
}
