{
  "id": "track_feel-the-groove-james-cole",
  "kind": "track",
  "slug": "feel-the-groove-james-cole",
  "title": "Feel The Groove",
  "aliases": [],
  "summary": "",
  "status": "stub",
  "createdAt": "2026-06-04",
  "updatedAt": "2026-06-04",
  "meta": {
    "primaryArtist": {
      "kind": "rapper",
      "slug": "james-cole"
    },
    "features": [],
    "album": {
      "kind": "album",
      "slug": "feel-the-groove-ep"
    },
    "producers": [],
    "year": 2019,
    "duration": "7:04",
    "trackNumber": 1,
    "genres": [],
    "deezerId": 662991032,
    "isrc": "CA5KR1923260",
    "rank": 21302,
    "explicit": false,
    "cover": "https://cdn-images.dzcdn.net/images/cover/27458da4e3b83aeb3429594094be3b71/1000x1000-000000-80-0-0.jpg",
    "previewUrl": "https://cdnt-preview.dzcdn.net/api/1/1/1/e/e/0/1ee7dede139644ed0d7db9d165bf3598.mp3?hdnea=exp=1780610475~acl=/api/1/1/1/e/e/0/1ee7dede139644ed0d7db9d165bf3598.mp3*~data=user_id=0,application_id=42~hmac=f7e2a85eab5e304d81fe5dd56597d686790e7455762c31d6f59a29cc9c8f0775",
    "bpm": null
  },
  "significance": {
    "why": "",
    "whatChanged": "",
    "context": "",
    "distinguishing": "",
    "oneLiner": ""
  },
  "timeline": [],
  "quotes": [],
  "faq": [],
  "hasLongform": false,
  "seo": {
    "noindex": true
  },
  "_deezer": {
    "fetchedAt": "2026-06-04T21:46:16.068Z",
    "source": "https://api.deezer.com/track/662991032",
    "raw": {
      "id": 662991032,
      "readable": true,
      "title": "Feel The Groove",
      "title_short": "Feel The Groove",
      "title_version": "",
      "isrc": "CA5KR1923260",
      "link": "https://www.deezer.com/track/662991032",
      "share": "https://www.deezer.com/track/662991032?utm_source=deezer&utm_content=track-662991032&utm_term=0_1780609575&utm_medium=web",
      "duration": 424,
      "track_position": 1,
      "disk_number": 1,
      "rank": 21302,
      "release_date": "2019-04-29",
      "explicit_lyrics": false,
      "explicit_content_lyrics": 0,
      "explicit_content_cover": 2,
      "preview": "https://cdnt-preview.dzcdn.net/api/1/1/1/e/e/0/1ee7dede139644ed0d7db9d165bf3598.mp3?hdnea=exp=1780610475~acl=/api/1/1/1/e/e/0/1ee7dede139644ed0d7db9d165bf3598.mp3*~data=user_id=0,application_id=42~hmac=f7e2a85eab5e304d81fe5dd56597d686790e7455762c31d6f59a29cc9c8f0775",
      "bpm": 0,
      "gain": -9.5,
      "available_countries": [
        "AE",
        "AF",
        "AG",
        "AI",
        "AL",
        "AM",
        "AO",
        "AQ",
        "AR",
        "AS",
        "AT",
        "AU",
        "AZ",
        "BA",
        "BB",
        "BD",
        "BE",
        "BF",
        "BG",
        "BH",
        "BI",
        "BJ",
        "BN",
        "BO",
        "BQ",
        "BR",
        "BT",
        "BV",
        "BW",
        "BY",
        "CA",
        "CC",
        "CD",
        "CF",
        "CG",
        "CH",
        "CI",
        "CK",
        "CL",
        "CM",
        "CN",
        "CO",
        "CR",
        "CU",
        "CV",
        "CW",
        "CX",
        "CY",
        "CZ",
        "DE",
        "DJ",
        "DK",
        "DM",
        "DO",
        "DZ",
        "EC",
        "EE",
        "EG",
        "EH",
        "ER",
        "ES",
        "ET",
        "FI",
        "FJ",
        "FK",
        "FM",
        "FR",
        "GA",
        "GB",
        "GD",
        "GE",
        "GH",
        "GM",
        "GN",
        "GQ",
        "GR",
        "GS",
        "GT",
        "GU",
        "GW",
        "HK",
        "HM",
        "HN",
        "HR",
        "HU",
        "ID",
        "IE",
        "IL",
        "IN",
        "IO",
        "IQ",
        "IR",
        "IS",
        "IT",
        "JM",
        "JO",
        "JP",
        "KE",
        "KG",
        "KH",
        "KI",
        "KM",
        "KN",
        "KP",
        "KR",
        "KW",
        "KY",
        "KZ",
        "LA",
        "LB",
        "LC",
        "LK",
        "LR",
        "LS",
        "LT",
        "LU",
        "LV",
        "LY",
        "MA",
        "MD",
        "ME",
        "MG",
        "MH",
        "MK",
        "ML",
        "MM",
        "MN",
        "MP",
        "MR",
        "MS",
        "MT",
        "MU",
        "MV",
        "MW",
        "MX",
        "MY",
        "MZ",
        "NA",
        "NE",
        "NF",
        "NG",
        "NI",
        "NL",
        "NO",
        "NP",
        "NR",
        "NU",
        "NZ",
        "OM",
        "PA",
        "PE",
        "PG",
        "PH",
        "PK",
        "PL",
        "PN",
        "PS",
        "PT",
        "PW",
        "PY",
        "QA",
        "RO",
        "RS",
        "RU",
        "RW",
        "SA",
        "SB",
        "SC",
        "SD",
        "SE",
        "SG",
        "SI",
        "SJ",
        "SK",
        "SL",
        "SN",
        "SO",
        "SS",
        "ST",
        "SV",
        "SX",
        "SY",
        "SZ",
        "TC",
        "TD",
        "TG",
        "TH",
        "TJ",
        "TK",
        "TL",
        "TM",
        "TN",
        "TO",
        "TR",
        "TV",
        "TW",
        "TZ",
        "UA",
        "UG",
        "UM",
        "US",
        "UY",
        "UZ",
        "VC",
        "VE",
        "VG",
        "VI",
        "VN",
        "VU",
        "WS",
        "YE",
        "ZA",
        "ZM",
        "ZW"
      ],
      "contributors": [
        {
          "id": 377020,
          "name": "James Cole",
          "link": "https://www.deezer.com/artist/377020",
          "share": "https://www.deezer.com/artist/377020?utm_source=deezer&utm_content=artist-377020&utm_term=0_1780609575&utm_medium=web",
          "picture": "https://api.deezer.com/artist/377020/image",
          "picture_small": "https://cdn-images.dzcdn.net/images/artist/1d7ca526b6b1b5ba61000820ac4aa24d/56x56-000000-80-0-0.jpg",
          "picture_medium": "https://cdn-images.dzcdn.net/images/artist/1d7ca526b6b1b5ba61000820ac4aa24d/250x250-000000-80-0-0.jpg",
          "picture_big": "https://cdn-images.dzcdn.net/images/artist/1d7ca526b6b1b5ba61000820ac4aa24d/500x500-000000-80-0-0.jpg",
          "picture_xl": "https://cdn-images.dzcdn.net/images/artist/1d7ca526b6b1b5ba61000820ac4aa24d/1000x1000-000000-80-0-0.jpg",
          "radio": true,
          "tracklist": "https://api.deezer.com/artist/377020/top?limit=50",
          "type": "artist",
          "role": "Main"
        }
      ],
      "md5_image": "27458da4e3b83aeb3429594094be3b71",
      "track_token": "AAAAAWoh8idqIwtnNzj0dxW3oD0c97bT_Xy98wVykvG6ep0_1BYSpbGzKSnhMrpoGz1u7-do7OBNYgSRa-zrRLF0imciRowzBoG6CGwm0LziGffYaT50gPAxnBSJUVl7c89dzUquGoP8LHABp0BgiLB-owNSIHjdk2MS0XM4tzA927zdaHaPUWRhDlRYvkLH3c7nHiuE7lgN9PEXiBoHl_2Vv3r4_9X1KkgS0_9mwbB2m7tP4mvucoM0O2VXTRsZi3K9F4BIQyJHRgr7beTpZ4UZjdu_TpbGejfYibISVk48jYTAR7x1gG-wjeMooSSqRF_in1CcJN5PQTEuSPSIEPjbQvmmJg9aWw3PwH9Z2wXvgSoRXIMW_X0DwcnqA0twUN1gTWk3",
      "artist": {
        "id": 377020,
        "name": "James Cole",
        "link": "https://www.deezer.com/artist/377020",
        "share": "https://www.deezer.com/artist/377020?utm_source=deezer&utm_content=artist-377020&utm_term=0_1780609575&utm_medium=web",
        "picture": "https://api.deezer.com/artist/377020/image",
        "picture_small": "https://cdn-images.dzcdn.net/images/artist/1d7ca526b6b1b5ba61000820ac4aa24d/56x56-000000-80-0-0.jpg",
        "picture_medium": "https://cdn-images.dzcdn.net/images/artist/1d7ca526b6b1b5ba61000820ac4aa24d/250x250-000000-80-0-0.jpg",
        "picture_big": "https://cdn-images.dzcdn.net/images/artist/1d7ca526b6b1b5ba61000820ac4aa24d/500x500-000000-80-0-0.jpg",
        "picture_xl": "https://cdn-images.dzcdn.net/images/artist/1d7ca526b6b1b5ba61000820ac4aa24d/1000x1000-000000-80-0-0.jpg",
        "radio": true,
        "tracklist": "https://api.deezer.com/artist/377020/top?limit=50",
        "type": "artist"
      },
      "album": {
        "id": 93138152,
        "title": "Feel The Groove EP",
        "link": "https://www.deezer.com/album/93138152",
        "cover": "https://api.deezer.com/album/93138152/image",
        "cover_small": "https://cdn-images.dzcdn.net/images/cover/27458da4e3b83aeb3429594094be3b71/56x56-000000-80-0-0.jpg",
        "cover_medium": "https://cdn-images.dzcdn.net/images/cover/27458da4e3b83aeb3429594094be3b71/250x250-000000-80-0-0.jpg",
        "cover_big": "https://cdn-images.dzcdn.net/images/cover/27458da4e3b83aeb3429594094be3b71/500x500-000000-80-0-0.jpg",
        "cover_xl": "https://cdn-images.dzcdn.net/images/cover/27458da4e3b83aeb3429594094be3b71/1000x1000-000000-80-0-0.jpg",
        "md5_image": "27458da4e3b83aeb3429594094be3b71",
        "release_date": "2019-04-29",
        "tracklist": "https://api.deezer.com/album/93138152/tracks",
        "type": "album"
      },
      "type": "track"
    }
  }
}
