{
  "id": "track_ya-sa-dame",
  "kind": "track",
  "slug": "ya-sa-dame",
  "title": "Ya sa",
  "status": "stub",
  "createdAt": "2026-06-06",
  "updatedAt": "2026-06-06",
  "meta": {
    "primaryArtist": {
      "kind": "rapper",
      "slug": "dame"
    },
    "features": [],
    "album": {
      "kind": "album",
      "slug": "fri-dom"
    },
    "producers": [],
    "year": 2023,
    "duration": "2:56",
    "trackNumber": 10,
    "genres": [
      "hip-hop"
    ],
    "deezerId": 2108969057,
    "isrc": "QZN882319845",
    "explicit": true,
    "cover": "https://cdn-images.dzcdn.net/images/cover/050c9ef010ec17ff9aa378d4e51e200d/1000x1000-000000-80-0-0.jpg",
    "previewUrl": "https://cdnt-preview.dzcdn.net/api/1/1/b/0/8/0/b082f706cde8f9cc695557e9ecb5b6aa.mp3?hdnea=exp=1780746771~acl=/api/1/1/b/0/8/0/b082f706cde8f9cc695557e9ecb5b6aa.mp3*~data=user_id=0,application_id=42~hmac=fafab49437c34f6d53519ca3ea78cc2b8048613ee2d90717b56378f7a10d6776"
  },
  "_deezer": {
    "fetchedAt": "2026-06-06T11:37:51.670Z",
    "raw": {
      "id": 2108969057,
      "readable": true,
      "title": "Ya sa",
      "title_short": "Ya sa",
      "title_version": "",
      "isrc": "QZN882319845",
      "link": "https://www.deezer.com/track/2108969057",
      "share": "https://www.deezer.com/track/2108969057?utm_source=deezer&utm_content=track-2108969057&utm_term=0_1780745871&utm_medium=web",
      "duration": 176,
      "track_position": 10,
      "disk_number": 1,
      "rank": 65530,
      "release_date": "2023-02-13",
      "explicit_lyrics": true,
      "explicit_content_lyrics": 1,
      "explicit_content_cover": 2,
      "preview": "https://cdnt-preview.dzcdn.net/api/1/1/b/0/8/0/b082f706cde8f9cc695557e9ecb5b6aa.mp3?hdnea=exp=1780746771~acl=/api/1/1/b/0/8/0/b082f706cde8f9cc695557e9ecb5b6aa.mp3*~data=user_id=0,application_id=42~hmac=fafab49437c34f6d53519ca3ea78cc2b8048613ee2d90717b56378f7a10d6776",
      "bpm": 0,
      "gain": -9.7,
      "available_countries": [
        "AE",
        "AF",
        "AG",
        "AI",
        "AL",
        "AM",
        "AO",
        "AQ",
        "AR",
        "AS",
        "AT",
        "AU",
        "AZ",
        "BA",
        "BB",
        "BD",
        "BE",
        "BF",
        "BG",
        "BH",
        "BI",
        "BJ",
        "BN",
        "BO",
        "BQ",
        "BR",
        "BT",
        "BV",
        "BW",
        "BY",
        "CA",
        "CC",
        "CD",
        "CF",
        "CG",
        "CH",
        "CI",
        "CK",
        "CL",
        "CM",
        "CN",
        "CO",
        "CR",
        "CU",
        "CV",
        "CW",
        "CX",
        "CY",
        "CZ",
        "DE",
        "DJ",
        "DK",
        "DM",
        "DO",
        "DZ",
        "EC",
        "EE",
        "EG",
        "EH",
        "ER",
        "ES",
        "ET",
        "FI",
        "FJ",
        "FK",
        "FM",
        "FR",
        "GA",
        "GB",
        "GD",
        "GE",
        "GH",
        "GM",
        "GN",
        "GQ",
        "GR",
        "GS",
        "GT",
        "GU",
        "GW",
        "HK",
        "HM",
        "HN",
        "HR",
        "HU",
        "ID",
        "IE",
        "IL",
        "IN",
        "IO",
        "IQ",
        "IR",
        "IS",
        "IT",
        "JM",
        "JO",
        "JP",
        "KE",
        "KG",
        "KH",
        "KI",
        "KM",
        "KN",
        "KP",
        "KR",
        "KW",
        "KY",
        "KZ",
        "LA",
        "LB",
        "LC",
        "LK",
        "LR",
        "LS",
        "LT",
        "LU",
        "LV",
        "LY",
        "MA",
        "MD",
        "ME",
        "MG",
        "MH",
        "MK",
        "ML",
        "MM",
        "MN",
        "MP",
        "MR",
        "MS",
        "MT",
        "MU",
        "MV",
        "MW",
        "MX",
        "MY",
        "MZ",
        "NA",
        "NE",
        "NF",
        "NG",
        "NI",
        "NL",
        "NO",
        "NP",
        "NR",
        "NU",
        "NZ",
        "OM",
        "PA",
        "PE",
        "PG",
        "PH",
        "PK",
        "PL",
        "PN",
        "PS",
        "PT",
        "PW",
        "PY",
        "QA",
        "RO",
        "RS",
        "RU",
        "RW",
        "SA",
        "SB",
        "SC",
        "SD",
        "SE",
        "SG",
        "SI",
        "SJ",
        "SK",
        "SL",
        "SN",
        "SO",
        "SS",
        "ST",
        "SV",
        "SX",
        "SY",
        "SZ",
        "TC",
        "TD",
        "TG",
        "TH",
        "TJ",
        "TK",
        "TL",
        "TM",
        "TN",
        "TO",
        "TR",
        "TV",
        "TW",
        "TZ",
        "UA",
        "UG",
        "UM",
        "US",
        "UY",
        "UZ",
        "VC",
        "VE",
        "VG",
        "VI",
        "VN",
        "VU",
        "WS",
        "YE",
        "ZA",
        "ZM",
        "ZW"
      ],
      "contributors": [
        {
          "id": 49495102,
          "name": "Dame",
          "link": "https://www.deezer.com/artist/49495102",
          "share": "https://www.deezer.com/artist/49495102?utm_source=deezer&utm_content=artist-49495102&utm_term=0_1780745871&utm_medium=web",
          "picture": "https://api.deezer.com/artist/49495102/image",
          "picture_small": "https://cdn-images.dzcdn.net/images/artist/55eff72abd1df56181b1c4b0a0e039e0/56x56-000000-80-0-0.jpg",
          "picture_medium": "https://cdn-images.dzcdn.net/images/artist/55eff72abd1df56181b1c4b0a0e039e0/250x250-000000-80-0-0.jpg",
          "picture_big": "https://cdn-images.dzcdn.net/images/artist/55eff72abd1df56181b1c4b0a0e039e0/500x500-000000-80-0-0.jpg",
          "picture_xl": "https://cdn-images.dzcdn.net/images/artist/55eff72abd1df56181b1c4b0a0e039e0/1000x1000-000000-80-0-0.jpg",
          "radio": true,
          "tracklist": "https://api.deezer.com/artist/49495102/top?limit=50",
          "type": "artist",
          "role": "Main"
        }
      ],
      "md5_image": "050c9ef010ec17ff9aa378d4e51e200d",
      "track_token": "AAAAAWokBo9qJR_P1lcjEJ0d9Hln9LqyDw0aQ8fvmMmrZIPtxRjwXNvBmIb2iAREGZJ_g_dJkcDTdayPNaaETS33QFu05Iyviw7d5uR_ULSLS1xZwkQDj7hYJGTRDzme71RxZmmajGodbNG_6Cuf_bsACiR8TiJdA-WJWgO3qkDqt0iX1ALKcU3fVsQMiutyE8ktSI_7PlHTh-8w0dNHPtaAJ5ypOzojfQzow_yDU8tUHWxByKYyBI1k5vwDZyvdBQcD5QGxNi8we2rj0nxVkWVCASXxHTVv71hA63nWaKc9qgDk9dIMwQpgnYtL6BSfyEe3EAhsNectve8EtjUNR-_YTKOcq2TxDbYaRqdH2eYhE-f5jPg8geveaQLPZ0b33hLkMSqK",
      "artist": {
        "id": 49495102,
        "name": "Dame",
        "link": "https://www.deezer.com/artist/49495102",
        "share": "https://www.deezer.com/artist/49495102?utm_source=deezer&utm_content=artist-49495102&utm_term=0_1780745871&utm_medium=web",
        "picture": "https://api.deezer.com/artist/49495102/image",
        "picture_small": "https://cdn-images.dzcdn.net/images/artist/55eff72abd1df56181b1c4b0a0e039e0/56x56-000000-80-0-0.jpg",
        "picture_medium": "https://cdn-images.dzcdn.net/images/artist/55eff72abd1df56181b1c4b0a0e039e0/250x250-000000-80-0-0.jpg",
        "picture_big": "https://cdn-images.dzcdn.net/images/artist/55eff72abd1df56181b1c4b0a0e039e0/500x500-000000-80-0-0.jpg",
        "picture_xl": "https://cdn-images.dzcdn.net/images/artist/55eff72abd1df56181b1c4b0a0e039e0/1000x1000-000000-80-0-0.jpg",
        "radio": true,
        "tracklist": "https://api.deezer.com/artist/49495102/top?limit=50",
        "type": "artist"
      },
      "album": {
        "id": 396700117,
        "title": "FRÍ DOM",
        "link": "https://www.deezer.com/album/396700117",
        "cover": "https://api.deezer.com/album/396700117/image",
        "cover_small": "https://cdn-images.dzcdn.net/images/cover/050c9ef010ec17ff9aa378d4e51e200d/56x56-000000-80-0-0.jpg",
        "cover_medium": "https://cdn-images.dzcdn.net/images/cover/050c9ef010ec17ff9aa378d4e51e200d/250x250-000000-80-0-0.jpg",
        "cover_big": "https://cdn-images.dzcdn.net/images/cover/050c9ef010ec17ff9aa378d4e51e200d/500x500-000000-80-0-0.jpg",
        "cover_xl": "https://cdn-images.dzcdn.net/images/cover/050c9ef010ec17ff9aa378d4e51e200d/1000x1000-000000-80-0-0.jpg",
        "md5_image": "050c9ef010ec17ff9aa378d4e51e200d",
        "release_date": "2023-02-13",
        "tracklist": "https://api.deezer.com/album/396700117/tracks",
        "type": "album"
      },
      "type": "track"
    }
  }
}
